{
	"enabledConfigurations": {
		"joystick:0": "AxisDefaultConfiguration"
	},
	"configurations": {
		"AxisDefaultConfiguration": {
			"configurationId": "AxisDefaultConfiguration",
			"configurationName":"Default Axis T8311 configuration",
			"controlOverrides":{
				"stick:0": {
					"invertX": "true"
				}
			},
			
			"eventMapping": {
				"stick:0": [
					{
						"ruleId": "rule0",
						"eventType": "stickMove",
						"actionType": "PtzContinuousMoveAction",
						"actionParameters": {
							"__comment": "just pairs (string, string)" 
						}
					}
				],
				
				"button:0":[
					{
						"ruleId": "rule1",
						"eventType": "buttonPressed",
						"actionType": "PtzActivatePresetByIndexAction",
						"actionParameters": {
							"presetIndex": "0"
						}
					}
				],
				"button:1":[
					{
						"ruleId": "rule2",
						"eventType": "buttonPressed",
						"actionType": "PtzActivatePresetByIndexAction",
						"actionParameters": {
							"presetIndex": "1"
						}
					}
				],
				"button:2":[
					{
						"ruleId": "rule3",
						"eventType": "buttonPressed",
						"actionType": "PtzActivatePresetByIndexAction",
						"actionParameters": {
							"presetIndex": "2"
						}
					}
				],
				"button:3":[
					{
						"ruleId": "rule4",
						"eventType": "buttonPressed",
						"actionType": "ToggleCurrentItemMaximizationStateAction",
						"actionParameters": {
						}
					}
				],
				"button:4":[
					{
						"ruleId": "rule5",
						"eventType": "buttonPressed",
						"actionType": "GoToPreviousItemAction",
						"actionParameters": {
						}
					}
				],
				"button:5":[
					{
						"ruleId": "rule6",
						"eventType": "buttonPressed",
						"actionType": "GoToNextItemAction",
						"actionParameters": {
						}
					}
				]
			}
		}
	}
}