<?xml version="1.0" encoding="UTF-8"?>
<SOAP-ENV:Envelope
    xmlns:SOAP-ENV="http://www.w3.org/2003/05/soap-envelope"
    xmlns:SOAP-ENC="http://www.w3.org/2003/05/soap-encoding"
    xmlns:xsi="http://www.w3.org/2001/XMLSchema-instance"
    xmlns:xsd="http://www.w3.org/2001/XMLSchema"
    xmlns:c14n="http://www.w3.org/2001/10/xml-exc-c14n#"
    xmlns:ds="http://www.w3.org/2000/09/xmldsig#"
    xmlns:saml1="urn:oasis:names:tc:SAML:1.0:assertion"
    xmlns:saml2="urn:oasis:names:tc:SAML:2.0:assertion"
    xmlns:wsu="http://docs.oasis-open.org/wss/2004/01/oasis-200401-wss-wssecurity-utility-1.0.xsd"
    xmlns:xenc="http://www.w3.org/2001/04/xmlenc#"
    xmlns:wsc="http://docs.oasis-open.org/ws-sx/ws-secureconversation/200512"
    xmlns:wsse="http://docs.oasis-open.org/wss/2004/01/oasis-200401-wss-wssecurity-secext-1.0.xsd"
    xmlns:chan="http://schemas.microsoft.com/ws/2005/02/duplex"
    xmlns:wsdd="http://schemas.xmlsoap.org/ws/2005/04/discovery"
    xmlns:wsdd5="http://tempuri.org/wsdd5.xsd"
    xmlns:wsa5="http://www.w3.org/2005/08/addressing"
    xmlns:xmime="http://tempuri.org/xmime.xsd"
    xmlns:xop="http://www.w3.org/2004/08/xop/include"
    xmlns:tt="http://www.onvif.org/ver10/schema"
    xmlns:wsrfbf="http://docs.oasis-open.org/wsrf/bf-2"
    xmlns:wstop="http://docs.oasis-open.org/wsn/t-1"
    xmlns:wsrfr="http://docs.oasis-open.org/wsrf/r-2"
    xmlns:onvifAnalytics-aeb="http://www.onvif.org/ver20/analytics/wsdl/AnalyticsEngineBinding"
    xmlns:onvifAnalytics-reb="http://www.onvif.org/ver20/analytics/wsdl/RuleEngineBinding"
    xmlns:onvifAnalytics="http://www.onvif.org/ver20/analytics/wsdl"
    xmlns:onvifDevice="http://www.onvif.org/ver10/device/wsdl"
    xmlns:onvifDeviceIO="http://www.onvif.org/ver10/deviceIO/wsdl"
    xmlns:onvifEvents-cpb="http://www.onvif.org/ver10/events/wsdl/CreatePullPointBinding"
    xmlns:onvifEvents-eb="http://www.onvif.org/ver10/events/wsdl/EventBinding"
    xmlns:onvifEvents-ncb="http://www.onvif.org/ver10/events/wsdl/NotificationConsumerBinding"
    xmlns:onvifEvents-npb="http://www.onvif.org/ver10/events/wsdl/NotificationProducerBinding"
    xmlns:onvifEvents-ppb="http://www.onvif.org/ver10/events/wsdl/PullPointBinding"
    xmlns:onvifEvents="http://www.onvif.org/ver10/events/wsdl"
    xmlns:onvifEvents-pps="http://www.onvif.org/ver10/events/wsdl/PullPointSubscriptionBinding"
    xmlns:onvifEvents-psmb="http://www.onvif.org/ver10/events/wsdl/PausableSubscriptionManagerBinding"
    xmlns:wsnt="http://docs.oasis-open.org/wsn/b-2"
    xmlns:onvifEvents-smb="http://www.onvif.org/ver10/events/wsdl/SubscriptionManagerBinding"
    xmlns:onvifImg="http://www.onvif.org/ver20/imaging/wsdl"
    xmlns:onvifMedia="http://www.onvif.org/ver10/media/wsdl"
    xmlns:onvifMedia2="http://www.onvif.org/ver20/media/wsdl"
    xmlns:onvifNetwork-dlb="http://www.onvif.org/ver10/network/wsdl/DiscoveryLookupBinding"
    xmlns:onvifNetwork-rdb="http://www.onvif.org/ver10/network/wsdl/RemoteDiscoveryBinding"
    xmlns:onvifNetwork="http://www.onvif.org/ver10/network/wsdl"
    xmlns:onvifPtz="http://www.onvif.org/ver20/ptz/wsdl">
 <!-- struct SOAP_ENV__Header *soap::header -->
 <SOAP-ENV:Header>
 </SOAP-ENV:Header>
 <SOAP-ENV:Body>
  <!-- __onvifMedia2__GetProfiles(..., _onvifMedia2__GetProfilesResponse &onvifMedia2__GetProfilesResponse) -->
  <onvifMedia2:GetProfilesResponse>
   <!-- std::vector<onvifMedia2__MediaProfile *> Profiles -->
   <!-- a repetition of 0 or more of the following -->
   <onvifMedia2:Profiles token="" fixed="false">
    <!-- std::string Name -->
    <onvifMedia2:Name></onvifMedia2:Name>
    <!-- onvifMedia2__ConfigurationSet *Configurations -->
    <onvifMedia2:Configurations>
     <!-- tt__VideoSourceConfiguration *VideoSource -->
     <onvifMedia2:VideoSource ViewMode="" token="">
      <!-- std::string Name -->
      <tt:Name></tt:Name>
      <!-- int UseCount -->
      <tt:UseCount>0</tt:UseCount>
      <!-- std::string SourceToken -->
      <tt:SourceToken></tt:SourceToken>
      <!-- tt__IntRectangle *Bounds -->
      <tt:Bounds x="0" y="0" width="0" height="0">
      </tt:Bounds>
      <!-- std::vector<struct soap_dom_element> __any -->
      <!-- a repetition of 0 or more of the following -->

      <!-- tt__VideoSourceConfigurationExtension *Extension -->
      <tt:Extension>
       <!-- tt__Rotate *Rotate -->
       <tt:Rotate>
        <!-- tt__RotateMode Mode -->
        <tt:Mode>OFF</tt:Mode>
        <!-- int *Degree -->
        <tt:Degree>0</tt:Degree>
        <!-- tt__RotateExtension *Extension -->
        <tt:Extension>
        </tt:Extension>
       </tt:Rotate>
       <!-- tt__VideoSourceConfigurationExtension2 *Extension -->
       <tt:Extension>
        <!-- std::vector<tt__LensDescription *> LensDescription -->
        <!-- a repetition of 0 or more of the following -->
        <tt:LensDescription FocalLength="0.0">
         <!-- tt__LensOffset *Offset -->
         <tt:Offset x="0.0" y="0.0">
         </tt:Offset>
         <!-- std::vector<tt__LensProjection *> Projection -->
         <!-- a repetition of 1 or more of the following -->
         <tt:Projection>
          <!-- float Angle -->
          <tt:Angle>0.0</tt:Angle>
          <!-- float Radius -->
          <tt:Radius>0.0</tt:Radius>
         </tt:Projection>
         <!-- float XFactor -->
         <tt:XFactor>0.0</tt:XFactor>
        </tt:LensDescription>
        <!-- tt__SceneOrientation *SceneOrientation -->
        <tt:SceneOrientation>
         <!-- tt__SceneOrientationMode Mode -->
         <tt:Mode>MANUAL</tt:Mode>
        </tt:SceneOrientation>
        <!-- std::vector<struct soap_dom_element> __any -->
        <!-- a repetition of 0 or more of the following -->

       </tt:Extension>
      </tt:Extension>
     </onvifMedia2:VideoSource>
     <!-- tt__AudioSourceConfiguration *AudioSource -->
     <onvifMedia2:AudioSource token="">
      <!-- std::string Name -->
      <tt:Name></tt:Name>
      <!-- int UseCount -->
      <tt:UseCount>0</tt:UseCount>
      <!-- std::string SourceToken -->
      <tt:SourceToken></tt:SourceToken>
      <!-- std::vector<struct soap_dom_element> __any -->
      <!-- a repetition of 0 or more of the following -->

     </onvifMedia2:AudioSource>
     <!-- tt__VideoEncoder2Configuration *VideoEncoder -->
     <onvifMedia2:VideoEncoder GovLength="0" Profile="" GuaranteedFrameRate="false" token="">
      <!-- std::string Name -->
      <tt:Name></tt:Name>
      <!-- int UseCount -->
      <tt:UseCount>0</tt:UseCount>
      <!-- std::string Encoding -->
      <tt:Encoding></tt:Encoding>
      <!-- tt__VideoResolution2 *Resolution -->
      <tt:Resolution>
       <!-- int Width -->
       <tt:Width>0</tt:Width>
       <!-- int Height -->
       <tt:Height>0</tt:Height>
       <!-- std::vector<struct soap_dom_element> __any -->
       <!-- a repetition of 0 or more of the following -->

      </tt:Resolution>
      <!-- tt__VideoRateControl2 *RateControl -->
      <tt:RateControl ConstantBitRate="false">
       <!-- float FrameRateLimit -->
       <tt:FrameRateLimit>0.0</tt:FrameRateLimit>
       <!-- int BitrateLimit -->
       <tt:BitrateLimit>0</tt:BitrateLimit>
       <!-- std::vector<struct soap_dom_element> __any -->
       <!-- a repetition of 0 or more of the following -->

      </tt:RateControl>
      <!-- tt__MulticastConfiguration *Multicast -->
      <tt:Multicast>
       <!-- tt__IPAddress *Address -->
       <tt:Address>
        <!-- tt__IPType Type -->
        <tt:Type>IPv4</tt:Type>
        <!-- std::string *IPv4Address -->
        <tt:IPv4Address></tt:IPv4Address>
        <!-- std::string *IPv6Address -->
        <tt:IPv6Address></tt:IPv6Address>
       </tt:Address>
       <!-- int Port -->
       <tt:Port>0</tt:Port>
       <!-- int TTL -->
       <tt:TTL>0</tt:TTL>
       <!-- bool AutoStart -->
       <tt:AutoStart>false</tt:AutoStart>
       <!-- std::vector<struct soap_dom_element> __any -->
       <!-- a repetition of 0 or more of the following -->

      </tt:Multicast>
      <!-- float Quality -->
      <tt:Quality>0.0</tt:Quality>
      <!-- std::vector<struct soap_dom_element> __any -->
      <!-- a repetition of 0 or more of the following -->

     </onvifMedia2:VideoEncoder>
     <!-- tt__AudioEncoder2Configuration *AudioEncoder -->
     <onvifMedia2:AudioEncoder token="">
      <!-- std::string Name -->
      <tt:Name></tt:Name>
      <!-- int UseCount -->
      <tt:UseCount>0</tt:UseCount>
      <!-- std::string Encoding -->
      <tt:Encoding></tt:Encoding>
      <!-- tt__MulticastConfiguration *Multicast -->
      <tt:Multicast>
       <!-- tt__IPAddress *Address -->
       <tt:Address>
        <!-- tt__IPType Type -->
        <tt:Type>IPv4</tt:Type>
        <!-- std::string *IPv4Address -->
        <tt:IPv4Address></tt:IPv4Address>
        <!-- std::string *IPv6Address -->
        <tt:IPv6Address></tt:IPv6Address>
       </tt:Address>
       <!-- int Port -->
       <tt:Port>0</tt:Port>
       <!-- int TTL -->
       <tt:TTL>0</tt:TTL>
       <!-- bool AutoStart -->
       <tt:AutoStart>false</tt:AutoStart>
       <!-- std::vector<struct soap_dom_element> __any -->
       <!-- a repetition of 0 or more of the following -->

      </tt:Multicast>
      <!-- int Bitrate -->
      <tt:Bitrate>0</tt:Bitrate>
      <!-- int SampleRate -->
      <tt:SampleRate>0</tt:SampleRate>
      <!-- std::vector<struct soap_dom_element> __any -->
      <!-- a repetition of 0 or more of the following -->

     </onvifMedia2:AudioEncoder>
     <!-- tt__VideoAnalyticsConfiguration *Analytics -->
     <onvifMedia2:Analytics token="">
      <!-- std::string Name -->
      <tt:Name></tt:Name>
      <!-- int UseCount -->
      <tt:UseCount>0</tt:UseCount>
      <!-- tt__AnalyticsEngineConfiguration *AnalyticsEngineConfiguration -->
      <tt:AnalyticsEngineConfiguration>
       <!-- std::vector<tt__Config *> AnalyticsModule -->
       <!-- a repetition of 0 or more of the following -->
       <tt:AnalyticsModule Name="" Type="xsd:string">
        <!-- tt__ItemList *Parameters -->
        <tt:Parameters>
        </tt:Parameters>
       </tt:AnalyticsModule>
       <!-- tt__AnalyticsEngineConfigurationExtension *Extension -->
       <tt:Extension>
        <!-- std::vector<struct soap_dom_element> __any -->
        <!-- a repetition of 0 or more of the following -->

       </tt:Extension>
      </tt:AnalyticsEngineConfiguration>
      <!-- tt__RuleEngineConfiguration *RuleEngineConfiguration -->
      <tt:RuleEngineConfiguration>
       <!-- std::vector<tt__Config *> Rule -->
       <!-- a repetition of 0 or more of the following -->
       <tt:Rule Name="" Type="xsd:string">
        <!-- tt__ItemList *Parameters -->
        <tt:Parameters>
        </tt:Parameters>
       </tt:Rule>
       <!-- tt__RuleEngineConfigurationExtension *Extension -->
       <tt:Extension>
        <!-- std::vector<struct soap_dom_element> __any -->
        <!-- a repetition of 0 or more of the following -->

       </tt:Extension>
      </tt:RuleEngineConfiguration>
      <!-- std::vector<struct soap_dom_element> __any -->
      <!-- a repetition of 0 or more of the following -->

     </onvifMedia2:Analytics>
     <!-- tt__PTZConfiguration *PTZ -->
     <onvifMedia2:PTZ MoveRamp="0" PresetRamp="0" PresetTourRamp="0" token="">
      <!-- std::string Name -->
      <tt:Name></tt:Name>
      <!-- int UseCount -->
      <tt:UseCount>0</tt:UseCount>
      <!-- std::string NodeToken -->
      <tt:NodeToken></tt:NodeToken>
      <!-- std::string *DefaultAbsolutePantTiltPositionSpace -->
      <tt:DefaultAbsolutePantTiltPositionSpace>http://www.example.com/schema/anyURI</tt:DefaultAbsolutePantTiltPositionSpace>
      <!-- std::string *DefaultAbsoluteZoomPositionSpace -->
      <tt:DefaultAbsoluteZoomPositionSpace>http://www.example.com/schema/anyURI</tt:DefaultAbsoluteZoomPositionSpace>
      <!-- std::string *DefaultRelativePanTiltTranslationSpace -->
      <tt:DefaultRelativePanTiltTranslationSpace>http://www.example.com/schema/anyURI</tt:DefaultRelativePanTiltTranslationSpace>
      <!-- std::string *DefaultRelativeZoomTranslationSpace -->
      <tt:DefaultRelativeZoomTranslationSpace>http://www.example.com/schema/anyURI</tt:DefaultRelativeZoomTranslationSpace>
      <!-- std::string *DefaultContinuousPanTiltVelocitySpace -->
      <tt:DefaultContinuousPanTiltVelocitySpace>http://www.example.com/schema/anyURI</tt:DefaultContinuousPanTiltVelocitySpace>
      <!-- std::string *DefaultContinuousZoomVelocitySpace -->
      <tt:DefaultContinuousZoomVelocitySpace>http://www.example.com/schema/anyURI</tt:DefaultContinuousZoomVelocitySpace>
      <!-- tt__PTZSpeed *DefaultPTZSpeed -->
      <tt:DefaultPTZSpeed>
       <!-- tt__Vector2D *PanTilt -->
       <tt:PanTilt x="0.0" y="0.0" space="http://www.example.com/schema/anyURI">
       </tt:PanTilt>
       <!-- tt__Vector1D *Zoom -->
       <tt:Zoom x="0.0" space="http://www.example.com/schema/anyURI">
       </tt:Zoom>
      </tt:DefaultPTZSpeed>
      <!-- LONG64 *DefaultPTZTimeout -->
      <tt:DefaultPTZTimeout>PT0S</tt:DefaultPTZTimeout>
      <!-- tt__PanTiltLimits *PanTiltLimits -->
      <tt:PanTiltLimits>
       <!-- tt__Space2DDescription *Range -->
       <tt:Range>
        <!-- std::string URI -->
        <tt:URI>http://www.example.com/schema/anyURI</tt:URI>
        <!-- tt__FloatRange *XRange -->
        <tt:XRange>
         <!-- float Min -->
         <tt:Min>0.0</tt:Min>
         <!-- float Max -->
         <tt:Max>0.0</tt:Max>
        </tt:XRange>
        <!-- tt__FloatRange *YRange -->
        <tt:YRange>
         <!-- float Min -->
         <tt:Min>0.0</tt:Min>
         <!-- float Max -->
         <tt:Max>0.0</tt:Max>
        </tt:YRange>
       </tt:Range>
      </tt:PanTiltLimits>
      <!-- tt__ZoomLimits *ZoomLimits -->
      <tt:ZoomLimits>
       <!-- tt__Space1DDescription *Range -->
       <tt:Range>
        <!-- std::string URI -->
        <tt:URI>http://www.example.com/schema/anyURI</tt:URI>
        <!-- tt__FloatRange *XRange -->
        <tt:XRange>
         <!-- float Min -->
         <tt:Min>0.0</tt:Min>
         <!-- float Max -->
         <tt:Max>0.0</tt:Max>
        </tt:XRange>
       </tt:Range>
      </tt:ZoomLimits>
      <!-- tt__PTZConfigurationExtension *Extension -->
      <tt:Extension>
       <!-- std::vector<struct soap_dom_element> __any -->
       <!-- a repetition of 0 or more of the following -->

       <!-- tt__PTControlDirection *PTControlDirection -->
       <tt:PTControlDirection>
        <!-- tt__EFlip *EFlip -->
        <tt:EFlip>
         <!-- tt__EFlipMode Mode -->
         <tt:Mode>OFF</tt:Mode>
        </tt:EFlip>
        <!-- tt__Reverse *Reverse -->
        <tt:Reverse>
         <!-- tt__ReverseMode Mode -->
         <tt:Mode>OFF</tt:Mode>
        </tt:Reverse>
        <!-- tt__PTControlDirectionExtension *Extension -->
        <tt:Extension>
        </tt:Extension>
       </tt:PTControlDirection>
       <!-- tt__PTZConfigurationExtension2 *Extension -->
       <tt:Extension>
        <!-- std::vector<struct soap_dom_element> __any -->
        <!-- a repetition of 0 or more of the following -->

       </tt:Extension>
      </tt:Extension>
     </onvifMedia2:PTZ>
     <!-- tt__MetadataConfiguration *Metadata -->
     <onvifMedia2:Metadata CompressionType="" GeoLocation="false" token="">
      <!-- std::string Name -->
      <tt:Name></tt:Name>
      <!-- int UseCount -->
      <tt:UseCount>0</tt:UseCount>
      <!-- tt__PTZFilter *PTZStatus -->
      <tt:PTZStatus>
       <!-- bool Status -->
       <tt:Status>false</tt:Status>
       <!-- bool Position -->
       <tt:Position>false</tt:Position>
      </tt:PTZStatus>
      <!-- tt__EventSubscription *Events -->
      <tt:Events>
       <!-- wsnt__FilterType *Filter -->
       <tt:Filter>
        <!-- std::vector<struct soap_dom_element> __any -->
        <!-- a repetition of 0 or more of the following -->

       </tt:Filter>
       <!-- _tt__EventSubscription_SubscriptionPolicy *SubscriptionPolicy -->
       <tt:SubscriptionPolicy>
        <!-- std::vector<struct soap_dom_element> __any -->
        <!-- a repetition of 0 or more of the following -->

       </tt:SubscriptionPolicy>
       <!-- std::vector<struct soap_dom_element> __any -->
       <!-- a repetition of 0 or more of the following -->

      </tt:Events>
      <!-- bool *Analytics -->
      <tt:Analytics>false</tt:Analytics>
      <!-- tt__MulticastConfiguration *Multicast -->
      <tt:Multicast>
       <!-- tt__IPAddress *Address -->
       <tt:Address>
        <!-- tt__IPType Type -->
        <tt:Type>IPv4</tt:Type>
        <!-- std::string *IPv4Address -->
        <tt:IPv4Address></tt:IPv4Address>
        <!-- std::string *IPv6Address -->
        <tt:IPv6Address></tt:IPv6Address>
       </tt:Address>
       <!-- int Port -->
       <tt:Port>0</tt:Port>
       <!-- int TTL -->
       <tt:TTL>0</tt:TTL>
       <!-- bool AutoStart -->
       <tt:AutoStart>false</tt:AutoStart>
       <!-- std::vector<struct soap_dom_element> __any -->
       <!-- a repetition of 0 or more of the following -->

      </tt:Multicast>
      <!-- LONG64 SessionTimeout -->
      <tt:SessionTimeout>PT0S</tt:SessionTimeout>
      <!-- std::vector<struct soap_dom_element> __any -->
      <!-- a repetition of 0 or more of the following -->

      <!-- tt__AnalyticsEngineConfiguration *AnalyticsEngineConfiguration -->
      <tt:AnalyticsEngineConfiguration>
       <!-- std::vector<tt__Config *> AnalyticsModule -->
       <!-- a repetition of 0 or more of the following -->
       <tt:AnalyticsModule Name="" Type="xsd:string">
        <!-- tt__ItemList *Parameters -->
        <tt:Parameters>
        </tt:Parameters>
       </tt:AnalyticsModule>
       <!-- tt__AnalyticsEngineConfigurationExtension *Extension -->
       <tt:Extension>
        <!-- std::vector<struct soap_dom_element> __any -->
        <!-- a repetition of 0 or more of the following -->

       </tt:Extension>
      </tt:AnalyticsEngineConfiguration>
      <!-- tt__MetadataConfigurationExtension *Extension -->
      <tt:Extension>
       <!-- std::vector<struct soap_dom_element> __any -->
       <!-- a repetition of 0 or more of the following -->

      </tt:Extension>
     </onvifMedia2:Metadata>
     <!-- tt__AudioOutputConfiguration *AudioOutput -->
     <onvifMedia2:AudioOutput token="">
      <!-- std::string Name -->
      <tt:Name></tt:Name>
      <!-- int UseCount -->
      <tt:UseCount>0</tt:UseCount>
      <!-- std::string OutputToken -->
      <tt:OutputToken></tt:OutputToken>
      <!-- std::string *SendPrimacy -->
      <tt:SendPrimacy>http://www.example.com/schema/anyURI</tt:SendPrimacy>
      <!-- int OutputLevel -->
      <tt:OutputLevel>0</tt:OutputLevel>
      <!-- std::vector<struct soap_dom_element> __any -->
      <!-- a repetition of 0 or more of the following -->

     </onvifMedia2:AudioOutput>
     <!-- tt__AudioDecoderConfiguration *AudioDecoder -->
     <onvifMedia2:AudioDecoder token="">
      <!-- std::string Name -->
      <tt:Name></tt:Name>
      <!-- int UseCount -->
      <tt:UseCount>0</tt:UseCount>
      <!-- std::vector<struct soap_dom_element> __any -->
      <!-- a repetition of 0 or more of the following -->

     </onvifMedia2:AudioDecoder>
     <!-- std::vector<struct soap_dom_element> __any -->
     <!-- a repetition of 0 or more of the following -->

    </onvifMedia2:Configurations>
   </onvifMedia2:Profiles>
  </onvifMedia2:GetProfilesResponse>
 </SOAP-ENV:Body>
</SOAP-ENV:Envelope>
